lsproxy/__init__.py
lsproxy/async_client.py
lsproxy/auth.py
lsproxy/client.py
lsproxy/modal.py
lsproxy/models.py
lsproxy_sdk-0.3.1.dist-info/METADATA
lsproxy_sdk-0.3.1.dist-info/WHEEL
lsproxy_sdk-0.3.1.dist-info/top_level.txt
lsproxy_sdk-0.3.1.dist-info/RECORD
