Metadata-Version: 2.2
Name: lsproxy-sdk
Version: 0.3.1
Summary: SDK for interacting with lsproxy container
Author-email: Maksim Ivanov <maksim@agenticlabs.com>, Robert McKnight <rob@agenticlabs.com>
License: MIT
Project-URL: Homepage, https://github.com/agentic-labs/lsproxy-sdk
Project-URL: Repository, https://github.com/agentic-labs/lsproxy-sdk.git
Requires-Python: >=3.10
Requires-Dist: httpx>=0.27.2
Requires-Dist: pydantic>=2.9.2
Provides-Extra: dev
Requires-Dist: ruff>=0.3.7; extra == "dev"
Provides-Extra: modal
Requires-Dist: modal>=0.56.4; extra == "modal"
